.gitignore
README.md
demo.py
setup.py
pybbcode/__init__.py
pybbcode.egg-info/PKG-INFO
pybbcode.egg-info/SOURCES.txt
pybbcode.egg-info/dependency_links.txt
pybbcode.egg-info/top_level.txt