Metadata-Version: 1.0
Name: pybbcode
Version: 1.0
Summary: PyBBCode -- A light yet powerful BB Code parser.
Home-page: http://github.com/pydsigner/pybbcode
Author: Daniel Foerster/pydsigner
Author-email: pydsigner@gmail.com
License: LGPLv3
Platform: UNKNOWN
Classifier: Development Status :: 4 - Beta
Classifier: Intended Audience :: Developers
Classifier: Operating System :: MacOS :: MacOS X
Classifier: Operating System :: Microsoft :: Windows
Classifier: Operating System :: POSIX
Classifier: Programming Language :: Python
